abzar/__init__.py
abzar/dict_merge.py
abzar/lousy_initable.py
abzar/nestable_dataclass.py
abzar/parse.py
abzar/singleton.py
abzar/timer.py
abzar/flask/__init__.py
abzar/flask/corsify.py
abzar/flask/nestable_blueprint.py
abzar-0.1.1.dist-info/LICENSE
abzar-0.1.1.dist-info/WHEEL
abzar-0.1.1.dist-info/METADATA
abzar-0.1.1.dist-info/RECORD
