Metadata-Version: 2.1
Name: abzar
Version: 0.1.1
Summary: Common python utils
Home-page: https://github.com/kamyar/abzar
License: UNKNOWN
Author: Kamyar Ghasemlou
Author-email: abzar@kamy.me
Classifier: License :: OSI Approved :: Apache Software License
